{"type":"Topology","objects":{"G_MP14_RAIL_LI":{"type":"GeometryCollection","geometries":[{"type":"LineString","arcs":[0,1]},{"type":"LineString","arcs":[2,1]},{"type":"LineString","arcs":[3]},{"type":"LineString","arcs":[4]},{"type":"LineString","arcs":[5]},{"type":"LineString","arcs":[6]},{"type":"LineString","arcs":[7]},{"type":"LineString","arcs":[8]},{"type":"LineString","arcs":[9]},{"type":"LineString","arcs":[10]},{"type":"LineString","arcs":[11]},{"type":"LineString","arcs":[12]},{"type":"LineString","arcs":[13]},{"type":"LineString","arcs":[14]},{"type":"LineString","arcs":[15]},{"type":"LineString","arcs":[16]},{"type":"LineString","arcs":[17]},{"type":"LineString","arcs":[18]},{"type":"LineString","arcs":[19]},{"type":"LineString","arcs":[20,21]},{"type":"LineString","arcs":[20,22]},{"type":"LineString","arcs":[23]},{"type":"MultiLineString","arcs":[[24],[25],[26],[27]]},{"type":"LineString","arcs":[28]},{"type":"LineString","arcs":[29]},{"type":"LineString","arcs":[30]},{"type":"LineString","arcs":[31]},{"type":"LineString","arcs":[32]},{"type":"LineString","arcs":[33]},{"type":"LineString","arcs":[34]},{"type":"LineString","arcs":[35]},{"type":"LineString","arcs":[36]},{"type":"LineString","arcs":[37]},{"type":"LineString","arcs":[38]},{"type":"LineString","arcs":[39]},{"type":"LineString","arcs":[40]},{"type":"LineString","arcs":[41]},{"type":"LineString","arcs":[42]},{"type":"LineString","arcs":[43]},{"type":"LineString","arcs":[44]},{"type":"LineString","arcs":[45]},{"type":"LineString","arcs":[46]},{"type":"LineString","arcs":[47]},{"type":"LineString","arcs":[48]},{"type":"LineString","arcs":[49]},{"type":"LineString","arcs":[50]},{"type":"LineString","arcs":[51]},{"type":"MultiLineString","arcs":[[52],[53]]},{"type":"MultiLineString","arcs":[[54],[55]]},{"type":"LineString","arcs":[56]},{"type":"LineString","arcs":[57]},{"type":"MultiLineString","arcs":[[58],[59],[60]]},{"type":"LineString","arcs":[61]},{"type":"LineString","arcs":[62]},{"type":"LineString","arcs":[63]},{"type":"LineString","arcs":[64]},{"type":"LineString","arcs":[65]},{"type":"LineString","arcs":[66]},{"type":"LineString","arcs":[67]},{"type":"LineString","arcs":[68]},{"type":"LineString","arcs":[69]},{"type":"LineString","arcs":[70]},{"type":"LineString","arcs":[71]},{"type":"LineString","arcs":[72]},{"type":"LineString","arcs":[73]},{"type":"LineString","arcs":[74]},{"type":"MultiLineString","arcs":[[75],[76]]},{"type":"LineString","arcs":[77]},{"type":"LineString","arcs":[78]},{"type":"LineString","arcs":[79]},{"type":"MultiLineString","arcs":[[80],[81]]},{"type":"LineString","arcs":[82]},{"type":"LineString","arcs":[83]},{"type":"LineString","arcs":[84]},{"type":"LineString","arcs":[85]},{"type":"LineString","arcs":[86]},{"type":"LineString","arcs":[87]},{"type":"LineString","arcs":[88]},{"type":"LineString","arcs":[89]},{"type":"LineString","arcs":[90]},{"type":"LineString","arcs":[91]},{"type":"LineString","arcs":[92]},{"type":"LineString","arcs":[93]},{"type":"LineString","arcs":[94]},{"type":"LineString","arcs":[95]},{"type":"LineString","arcs":[96]},{"type":"LineString","arcs":[97]},{"type":"LineString","arcs":[98]},{"type":"MultiLineString","arcs":[[99],[100],[101]]},{"type":"LineString","arcs":[102]},{"type":"LineString","arcs":[103]},{"type":"LineString","arcs":[104]},{"type":"LineString","arcs":[105]},{"type":"LineString","arcs":[106]},{"type":"LineString","arcs":[107]},{"type":"LineString","arcs":[108]},{"type":"LineString","arcs":[109]},{"type":"LineString","arcs":[110]},{"type":"LineString","arcs":[111]},{"type":"LineString","arcs":[112]},{"type":"LineString","arcs":[113]},{"type":"LineString","arcs":[114]},{"type":"LineString","arcs":[115]},{"type":"LineString","arcs":[116]},{"type":"LineString","arcs":[117]},{"type":"LineString","arcs":[118]},{"type":"LineString","arcs":[119]},{"type":"LineString","arcs":[120]},{"type":"LineString","arcs":[121]},{"type":"LineString","arcs":[122]},{"type":"LineString","arcs":[123]},{"type":"LineString","arcs":[124]},{"type":"LineString","arcs":[125]},{"type":"LineString","arcs":[126]},{"type":"LineString","arcs":[127]},{"type":"LineString","arcs":[128]},{"type":"LineString","arcs":[129]},{"type":"LineString","arcs":[130]},{"type":"LineString","arcs":[131]},{"type":"LineString","arcs":[132]},{"type":"LineString","arcs":[133]},{"type":"LineString","arcs":[134]},{"type":"LineString","arcs":[135]},{"type":"LineString","arcs":[136]},{"type":"LineString","arcs":[137]},{"type":"LineString","arcs":[138]},{"type":"LineString","arcs":[139]},{"type":"LineString","arcs":[140]},{"type":"LineString","arcs":[141]},{"type":"LineString","arcs":[142]},{"type":"LineString","arcs":[143]},{"type":"LineString","arcs":[144]},{"type":"LineString","arcs":[145]},{"type":"LineString","arcs":[146]},{"type":"LineString","arcs":[147]},{"type":"LineString","arcs":[148]},{"type":"LineString","arcs":[149]},{"type":"MultiLineString","arcs":[[150],[151]]},{"type":"LineString","arcs":[152]},{"type":"LineString","arcs":[153]},{"type":"LineString","arcs":[154]},{"type":"LineString","arcs":[155]},{"type":"MultiLineString","arcs":[[156],[157],[158]]},{"type":"LineString","arcs":[159]},{"type":"MultiLineString","arcs":[[160],[161],[162]]},{"type":"LineString","arcs":[163]},{"type":"LineString","arcs":[164,165]},{"type":"LineString","arcs":[166]},{"type":"LineString","arcs":[167,168]},{"type":"LineString","arcs":[169]},{"type":"LineString","arcs":[170,171]},{"type":"LineString","arcs":[172]},{"type":"LineString","arcs":[173]},{"type":"LineString","arcs":[174]},{"type":"LineString","arcs":[175]},{"type":"LineString","arcs":[176]},{"type":"LineString","arcs":[177]},{"type":"LineString","arcs":[178]},{"type":"LineString","arcs":[179]},{"type":"LineString","arcs":[180]},{"type":"LineString","arcs":[181]},{"type":"LineString","arcs":[182]},{"type":"LineString","arcs":[183]},{"type":"LineString","arcs":[184]},{"type":"LineString","arcs":[185]},{"type":"LineString","arcs":[186]},{"type":"LineString","arcs":[187]},{"type":"LineString","arcs":[188]},{"type":"LineString","arcs":[189]},{"type":"LineString","arcs":[190]},{"type":"LineString","arcs":[191]},{"type":"LineString","arcs":[192]},{"type":"LineString","arcs":[193]},{"type":"MultiLineString","arcs":[[194,195],[196]]},{"type":"MultiLineString","arcs":[[197,198],[199]]},{"type":"LineString","arcs":[200]},{"type":"LineString","arcs":[201]},{"type":"LineString","arcs":[202]},{"type":"LineString","arcs":[203]},{"type":"LineString","arcs":[204]},{"type":"LineString","arcs":[205]},{"type":"LineString","arcs":[206]},{"type":"LineString","arcs":[207]},{"type":"LineString","arcs":[208]},{"type":"MultiLineString","arcs":[[209],[210]]},{"type":"LineString","arcs":[211]},{"type":"LineString","arcs":[212]},{"type":"MultiLineString","arcs":[[213],[214],[215],[216]]},{"type":"LineString","arcs":[217]},{"type":"LineString","arcs":[218]},{"type":"LineString","arcs":[219]},{"type":"LineString","arcs":[220]},{"type":"LineString","arcs":[221]},{"type":"LineString","arcs":[222]},{"type":"LineString","arcs":[223]},{"type":"MultiLineString","arcs":[[224],[225]]},{"type":"LineString","arcs":[226]},{"type":"LineString","arcs":[227]},{"type":"LineString","arcs":[228]},{"type":"LineString","arcs":[229]},{"type":"LineString","arcs":[230]},{"type":"LineString","arcs":[231]},{"type":"LineString","arcs":[232]},{"type":"LineString","arcs":[233]},{"type":"LineString","arcs":[234]},{"type":"LineString","arcs":[235]},{"type":"LineString","arcs":[236]},{"type":"LineString","arcs":[237]},{"type":"LineString","arcs":[238]},{"type":"LineString","arcs":[239]},{"type":"LineString","arcs":[240]},{"type":"LineString","arcs":[241]},{"type":"LineString","arcs":[242]},{"type":"LineString","arcs":[243]},{"type":"LineString","arcs":[244]},{"type":"LineString","arcs":[245]},{"type":"MultiLineString","arcs":[[246],[247]]},{"type":"LineString","arcs":[248]},{"type":"LineString","arcs":[249]},{"type":"LineString","arcs":[250]},{"type":"LineString","arcs":[251]},{"type":"LineString","arcs":[252]},{"type":"LineString","arcs":[253]},{"type":"LineString","arcs":[254]},{"type":"MultiLineString","arcs":[[255],[256]]},{"type":"LineString","arcs":[257]},{"type":"LineString","arcs":[258]},{"type":"LineString","arcs":[259]},{"type":"LineString","arcs":[260]},{"type":"LineString","arcs":[261]},{"type":"LineString","arcs":[262]},{"type":"LineString","arcs":[263]},{"type":"LineString","arcs":[264]},{"type":"LineString","arcs":[265]},{"type":"LineString","arcs":[266]},{"type":"LineString","arcs":[267]},{"type":"LineString","arcs":[268]},{"type":"LineString","arcs":[269]},{"type":"LineString","arcs":[270]},{"type":"LineString","arcs":[271]},{"type":"LineString","arcs":[272]},{"type":"LineString","arcs":[273]},{"type":"LineString","arcs":[274]},{"type":"LineString","arcs":[275]},{"type":"LineString","arcs":[276]},{"type":"LineString","arcs":[277]},{"type":"LineString","arcs":[278]},{"type":"LineString","arcs":[279]},{"type":"LineString","arcs":[280]},{"type":"LineString","arcs":[281]},{"type":"LineString","arcs":[282]},{"type":"LineString","arcs":[283]},{"type":"MultiLineString","arcs":[[284],[285],[286]]},{"type":"LineString","arcs":[287]},{"type":"LineString","arcs":[288]},{"type":"LineString","arcs":[289]},{"type":"LineString","arcs":[290]},{"type":"MultiLineString","arcs":[[291],[292]]},{"type":"LineString","arcs":[293]},{"type":"LineString","arcs":[294]},{"type":"LineString","arcs":[295]},{"type":"LineString","arcs":[296]},{"type":"LineString","arcs":[297]},{"type":"LineString","arcs":[298]},{"type":"LineString","arcs":[299]},{"type":"LineString","arcs":[300]},{"type":"LineString","arcs":[301]},{"type":"LineString","arcs":[302]},{"type":"LineString","arcs":[303]},{"type":"LineString","arcs":[304]},{"type":"LineString","arcs":[305]},{"type":"LineString","arcs":[306]},{"type":"LineString","arcs":[307]},{"type":"LineString","arcs":[308]},{"type":"LineString","arcs":[309]},{"type":"LineString","arcs":[310]},{"type":"LineString","arcs":[311]},{"type":"LineString","arcs":[312]},{"type":"LineString","arcs":[313]},{"type":"LineString","arcs":[314]},{"type":"LineString","arcs":[315]},{"type":"LineString","arcs":[316]},{"type":"LineString","arcs":[317]},{"type":"LineString","arcs":[318]},{"type":"LineString","arcs":[319]},{"type":"LineString","arcs":[320]},{"type":"LineString","arcs":[321]},{"type":"LineString","arcs":[322]},{"type":"LineString","arcs":[323]},{"type":"LineString","arcs":[324]},{"type":"MultiLineString","arcs":[[325],[326],[327]]},{"type":"LineString","arcs":[328]},{"type":"LineString","arcs":[329]},{"type":"MultiLineString","arcs":[[330],[331],[332]]},{"type":"LineString","arcs":[333]},{"type":"LineString","arcs":[334]},{"type":"LineString","arcs":[335]},{"type":"LineString","arcs":[336]},{"type":"LineString","arcs":[337]},{"type":"LineString","arcs":[338]},{"type":"LineString","arcs":[339]},{"type":"LineString","arcs":[340]},{"type":"LineString","arcs":[341]},{"type":"LineString","arcs":[342]},{"type":"LineString","arcs":[343]},{"type":"LineString","arcs":[344]},{"type":"LineString","arcs":[345]},{"type":"LineString","arcs":[346]},{"type":"LineString","arcs":[347]},{"type":"LineString","arcs":[348]},{"type":"LineString","arcs":[349]},{"type":"LineString","arcs":[350]},{"type":"LineString","arcs":[351]},{"type":"LineString","arcs":[352]},{"type":"LineString","arcs":[353]},{"type":"LineString","arcs":[354]},{"type":"LineString","arcs":[355]},{"type":"LineString","arcs":[356]},{"type":"LineString","arcs":[357]},{"type":"LineString","arcs":[358]},{"type":"LineString","arcs":[359]},{"type":"LineString","arcs":[360]},{"type":"LineString","arcs":[361]},{"type":"LineString","arcs":[362]},{"type":"LineString","arcs":[363]},{"type":"MultiLineString","arcs":[[364],[365],[366]]},{"type":"LineString","arcs":[367]},{"type":"LineString","arcs":[368]},{"type":"LineString","arcs":[369]},{"type":"LineString","arcs":[370]},{"type":"LineString","arcs":[371]},{"type":"LineString","arcs":[372]},{"type":"LineString","arcs":[373]},{"type":"LineString","arcs":[374]},{"type":"LineString","arcs":[375]},{"type":"MultiLineString","arcs":[[376],[377],[378]]},{"type":"LineString","arcs":[379,380,381,382,383,384,385]},{"type":"LineString","arcs":[386,387,388,389,390]},{"type":"LineString","arcs":[391]},{"type":"LineString","arcs":[392]},{"type":"LineString","arcs":[393]},{"type":"LineString","arcs":[394]},{"type":"LineString","arcs":[395]},{"type":"LineString","arcs":[396]},{"type":"LineString","arcs":[397]},{"type":"LineString","arcs":[398]},{"type":"LineString","arcs":[399]},{"type":"LineString","arcs":[400]},{"type":"LineString","arcs":[401]},{"type":"LineString","arcs":[402]},{"type":"MultiLineString","arcs":[[403],[404],[405],[406],[407],[408]]},{"type":"MultiLineString","arcs":[[409],[410]]},{"type":"LineString","arcs":[411]},{"type":"MultiLineString","arcs":[[412],[413]]},{"type":"LineString","arcs":[414]},{"type":"MultiLineString","arcs":[[415],[416]]},{"type":"LineString","arcs":[417]},{"type":"LineString","arcs":[418]},{"type":"LineString","arcs":[419]},{"type":"MultiLineString","arcs":[[420],[421],[422]]},{"type":"MultiLineString","arcs":[[423],[424],[425]]},{"type":"LineString","arcs":[426]},{"type":"LineString","arcs":[427]},{"type":"LineString","arcs":[428]},{"type":"LineString","arcs":[429]},{"type":"LineString","arcs":[430]},{"type":"MultiLineString","arcs":[[431],[432]]},{"type":"MultiLineString","arcs":[[433],[434]]},{"type":"LineString","arcs":[435]},{"type":"LineString","arcs":[436]},{"type":"LineString","arcs":[437]},{"type":"LineString","arcs":[438]},{"type":"LineString","arcs":[439]},{"type":"MultiLineString","arcs":[[440],[441],[442],[443]]},{"type":"LineString","arcs":[444]},{"type":"LineString","arcs":[445]},{"type":"LineString","arcs":[446]},{"type":"MultiLineString","arcs":[[447],[448],[449]]},{"type":"LineString","arcs":[450]},{"type":"LineString","arcs":[451]},{"type":"MultiLineString","arcs":[[452],[453]]},{"type":"LineString","arcs":[454]},{"type":null},{"type":"LineString","arcs":[455]},{"type":"LineString","arcs":[456]},{"type":"LineString","arcs":[457]},{"type":"LineString","arcs":[458,459,460,461,462,463,464]},{"type":"LineString","arcs":[465]},{"type":"LineString","arcs":[466]},{"type":"LineString","arcs":[467]},{"type":"LineString","arcs":[468]},{"type":"LineString","arcs":[469]},{"type":"LineString","arcs":[470]},{"type":"LineString","arcs":[471]},{"type":"LineString","arcs":[472]},{"type":"LineString","arcs":[473]},{"type":"LineString","arcs":[474]},{"type":"LineString","arcs":[475]},{"type":"LineString","arcs":[476]},{"type":"LineString","arcs":[477]},{"type":"LineString","arcs":[478]},{"type":"LineString","arcs":[479]},{"type":"LineString","arcs":[480]},{"type":"LineString","arcs":[481]},{"type":"LineString","arcs":[482]},{"type":"LineString","arcs":[483]},{"type":"MultiLineString","arcs":[[484],[485],[486],[487]]},{"type":"LineString","arcs":[488]},{"type":"LineString","arcs":[489]},{"type":"MultiLineString","arcs":[[490],[491],[492]]},{"type":"MultiLineString","arcs":[[493],[494],[495],[496],[497],[498]]},{"type":"MultiLineString","arcs":[[499],[500]]},{"type":"LineString","arcs":[501]},{"type":"MultiLineString","arcs":[[502],[503],[504],[505],[506],[507],[508],[509]]},{"type":"LineString","arcs":[510]},{"type":"LineString","arcs":[511]},{"type":"LineString","arcs":[512]},{"type":"LineString","arcs":[513]},{"type":"LineString","arcs":[514]},{"type":"MultiLineString","arcs":[[515],[516],[517],[518]]},{"type":"LineString","arcs":[519]},{"type":"LineString","arcs":[520]},{"type":"MultiLineString","arcs":[[521],[522],[523]]},{"type":"LineString","arcs":[524]},{"type":"LineString","arcs":[525]},{"type":"LineString","arcs":[526]},{"type":"LineString","arcs":[527]},{"type":"LineString","arcs":[528]},{"type":"LineString","arcs":[529]},{"type":"LineString","arcs":[530]},{"type":"LineString","arcs":[531]},{"type":"LineString","arcs":[532]},{"type":"LineString","arcs":[533]},{"type":"LineString","arcs":[534]},{"type":"LineString","arcs":[535]},{"type":"LineString","arcs":[536]},{"type":"MultiLineString","arcs":[[537],[538],[539]]},{"type":"LineString","arcs":[540]},{"type":"LineString","arcs":[541]},{"type":"LineString","arcs":[542]},{"type":"LineString","arcs":[543]},{"type":"MultiLineString","arcs":[[544],[545]]},{"type":"LineString","arcs":[546]},{"type":"LineString","arcs":[547]},{"type":"LineString","arcs":[548]},{"type":"LineString","arcs":[549]},{"type":"LineString","arcs":[550]},{"type":"LineString","arcs":[551]},{"type":"LineString","arcs":[552]},{"type":"LineString","arcs":[553]},{"type":"LineString","arcs":[554]},{"type":"LineString","arcs":[555]},{"type":"LineString","arcs":[556]},{"type":"LineString","arcs":[557]},{"type":"LineString","arcs":[558]},{"type":"LineString","arcs":[458,559,560]},{"type":"LineString","arcs":[561]},{"type":"LineString","arcs":[562]},{"type":"LineString","arcs":[563]},{"type":"LineString","arcs":[564]},{"type":"LineString","arcs":[565]},{"type":"LineString","arcs":[566]},{"type":"LineString","arcs":[567]},{"type":"LineString","arcs":[568]},{"type":"LineString","arcs":[569]},{"type":"LineString","arcs":[570]},{"type":"LineString","arcs":[571]},{"type":"LineString","arcs":[572]},{"type":"LineString","arcs":[573]},{"type":"LineString","arcs":[574]},{"type":"LineString","arcs":[575]},{"type":"LineString","arcs":[576]},{"type":"LineString","arcs":[577,578]},{"type":"LineString","arcs":[579]},{"type":"MultiLineString","arcs":[[580],[581]]},{"type":"LineString","arcs":[582]},{"type":"LineString","arcs":[583,584,585]},{"type":"LineString","arcs":[586]},{"type":"LineString","arcs":[587]},{"type":"LineString","arcs":[588]},{"type":"LineString","arcs":[589]},{"type":"LineString","arcs":[590]},{"type":"LineString","arcs":[591]},{"type":"LineString","arcs":[592]},{"type":"LineString","arcs":[593]},{"type":"LineString","arcs":[594]},{"type":"LineString","arcs":[595]},{"type":"LineString","arcs":[596]},{"type":"LineString","arcs":[597]},{"type":"LineString","arcs":[598]},{"type":"LineString","arcs":[599]},{"type":"LineString","arcs":[600]},{"type":"LineString","arcs":[601]},{"type":"LineString","arcs":[602]},{"type":"LineString","arcs":[603]},{"type":"LineString","arcs":[604]},{"type":"LineString","arcs":[605]},{"type":"LineString","arcs":[606]},{"type":"MultiLineString","arcs":[[607],[608]]},{"type":"LineString","arcs":[609]},{"type":"LineString","arcs":[610]},{"type":"LineString","arcs":[611]},{"type":"LineString","arcs":[612]},{"type":"LineString","arcs":[613]},{"type":"LineString","arcs":[614]},{"type":"LineString","arcs":[615]},{"type":"LineString","arcs":[616]},{"type":"LineString","arcs":[617]},{"type":"MultiLineString","arcs":[[618],[619]]},{"type":"MultiLineString","arcs":[[620],[621]]},{"type":"LineString","arcs":[622]},{"type":"LineString","arcs":[623]},{"type":"LineString","arcs":[624]},{"type":"LineString","arcs":[625]},{"type":"LineString","arcs":[626]},{"type":"LineString","arcs":[627]},{"type":"LineString","arcs":[628]},{"type":"LineString","arcs":[629]},{"type":"LineString","arcs":[630]},{"type":"LineString","arcs":[631]},{"type":"LineString","arcs":[632]},{"type":"LineString","arcs":[633]},{"type":"LineString","arcs":[634]},{"type":"LineString","arcs":[635]},{"type":"LineString","arcs":[636]},{"type":"LineString","arcs":[637]},{"type":"LineString","arcs":[638]},{"type":"LineString","arcs":[639]},{"type":"LineString","arcs":[640]},{"type":"LineString","arcs":[641]},{"type":"LineString","arcs":[642]},{"type":"LineString","arcs":[643]},{"type":"LineString","arcs":[644]},{"type":"LineString","arcs":[645]},{"type":"LineString","arcs":[646]},{"type":"LineString","arcs":[647]},{"type":"LineString","arcs":[648]},{"type":"LineString","arcs":[649]},{"type":"LineString","arcs":[650]},{"type":"LineString","arcs":[651]},{"type":"LineString","arcs":[652]},{"type":"LineString","arcs":[653]},{"type":"LineString","arcs":[654]},{"type":"LineString","arcs":[655]},{"type":"LineString","arcs":[656]},{"type":"LineString","arcs":[657]},{"type":"LineString","arcs":[658]},{"type":"MultiLineString","arcs":[[659],[660],[661],[662,663]]},{"type":"MultiLineString","arcs":[[664,665],[666,667],[668]]},{"type":"LineString","arcs":[669]},{"type":"LineString","arcs":[670]},{"type":"LineString","arcs":[671]},{"type":"LineString","arcs":[672,673]},{"type":"LineString","arcs":[674]},{"type":"LineString","arcs":[675]},{"type":"LineString","arcs":[676]},{"type":"MultiLineString","arcs":[[677],[678]]},{"type":"LineString","arcs":[679]},{"type":"LineString","arcs":[680,681]},{"type":"LineString","arcs":[682]},{"type":"LineString","arcs":[683]},{"type":"LineString","arcs":[684]},{"type":"LineString","arcs":[685]},{"type":"LineString","arcs":[686]},{"type":"LineString","arcs":[687]},{"type":"LineString","arcs":[688]},{"type":"MultiLineString","arcs":[[689],[690],[691]]},{"type":"LineString","arcs":[692]},{"type":"MultiLineString","arcs":[[693],[694]]},{"type":"LineString","arcs":[695]},{"type":"LineString","arcs":[696]},{"type":"LineString","arcs":[697]},{"type":"LineString","arcs":[698]},{"type":"LineString","arcs":[699]},{"type":"LineString","arcs":[700]},{"type":"LineString","arcs":[701]},{"type":"LineString","arcs":[702]},{"type":"MultiLineString","arcs":[[703],[704],[705]]},{"type":"LineString","arcs":[706]},{"type":"LineString","arcs":[707]},{"type":"LineString","arcs":[708]},{"type":"LineString","arcs":[709]},{"type":"MultiLineString","arcs":[[710],[711]]},{"type":"LineString","arcs":[712]},{"type":"LineString","arcs":[713]},{"type":"LineString","arcs":[714]},{"type":"LineString","arcs":[715]},{"type":"LineString","arcs":[716]},{"type":"LineString","arcs":[717]},{"type":"LineString","arcs":[718]},{"type":"LineString","arcs":[719]},{"type":"MultiLineString","arcs":[[720],[721]]},{"type":"LineString","arcs":[722]},{"type":"MultiLineString","arcs":[[723],[724],[725]]},{"type":"MultiLineString","arcs":[[726],[727]]},{"type":"LineString","arcs":[728]},{"type":"LineString","arcs":[729]},{"type":"LineString","arcs":[730]},{"type":"LineString","arcs":[731]},{"type":"LineString","arcs":[732]},{"type":"LineString","arcs":[733]},{"type":"LineString","arcs":[734]},{"type":"LineString","arcs":[735]},{"type":"LineString","arcs":[736]},{"type":"LineString","arcs":[737]},{"type":"LineString","arcs":[738]},{"type":"LineString","arcs":[739]},{"type":"LineString","arcs":[740]},{"type":"LineString","arcs":[741]},{"type":"LineString","arcs":[742]},{"type":"LineString","arcs":[743]},{"type":"LineString","arcs":[744]},{"type":"LineString","arcs":[745]},{"type":"LineString","arcs":[746]},{"type":"LineString","arcs":[747]},{"type":"LineString","arcs":[748]},{"type":"LineString","arcs":[749]},{"type":"LineString","arcs":[750]},{"type":"LineString","arcs":[751]},{"type":"LineString","arcs":[752]},{"type":"LineString","arcs":[753]},{"type":"LineString","arcs":[754]},{"type":"LineString","arcs":[755]},{"type":"LineString","arcs":[756]},{"type":"LineString","arcs":[757]},{"type":"LineString","arcs":[758]},{"type":"LineString","arcs":[759]},{"type":"LineString","arcs":[760]},{"type":"LineString","arcs":[761]},{"type":"LineString","arcs":[762]},{"type":"LineString","arcs":[763]},{"type":"LineString","arcs":[764]},{"type":"LineString","arcs":[765]},{"type":"LineString","arcs":[766]},{"type":"LineString","arcs":[767]},{"type":"LineString","arcs":[768]},{"type":"LineString","arcs":[769]},{"type":"LineString","arcs":[770]},{"type":"LineString","arcs":[771]},{"type":"MultiLineString","arcs":[[772],[773],[774]]},{"type":"LineString","arcs":[775]},{"type":"LineString","arcs":[776]},{"type":"LineString","arcs":[777]},{"type":"LineString","arcs":[778]},{"type":"LineString","arcs":[779]},{"type":"MultiLineString","arcs":[[780],[781],[782],[783]]},{"type":"MultiLineString","arcs":[[784],[785],[786],[787],[788]]},{"type":"LineString","arcs":[789]},{"type":"LineString","arcs":[790]},{"type":"LineString","arcs":[791]},{"type":"LineString","arcs":[792]},{"type":"LineString","arcs":[793]},{"type":"LineString","arcs":[794]},{"type":"LineString","arcs":[795]},{"type":"LineString","arcs":[796]},{"type":"LineString","arcs":[797]},{"type":"LineString","arcs":[798]},{"type":"LineString","arcs":[799]},{"type":"LineString","arcs":[800]},{"type":"LineString","arcs":[801]},{"type":"LineString","arcs":[802]},{"type":"LineString","arcs":[803]},{"type":"MultiLineString","arcs":[[804],[805]]},{"type":"LineString","arcs":[806]},{"type":"LineString","arcs":[807]},{"type":"LineString","arcs":[808]},{"type":"LineString","arcs":[809]},{"type":"LineString","arcs":[810]},{"type":"LineString","arcs":[811]},{"type":"LineString","arcs":[812]},{"type":"LineString","arcs":[813]},{"type":"LineString","arcs":[814]},{"type":"LineString","arcs":[815]},{"type":"LineString","arcs":[816]},{"type":"LineString","arcs":[817]},{"type":"LineString","arcs":[818]},{"type":"MultiLineString","arcs":[[819],[820]]},{"type":"LineString","arcs":[821]},{"type":"LineString","arcs":[822]},{"type":"LineString","arcs":[823]},{"type":"LineString","arcs":[824]},{"type":"LineString","arcs":[825]},{"type":"LineString","arcs":[826]},{"type":"LineString","arcs":[827]},{"type":"LineString","arcs":[828]},{"type":"LineString","arcs":[829]},{"type":"LineString","arcs":[830]},{"type":"MultiLineString","arcs":[[831],[832],[833]]},{"type":"LineString","arcs":[834]},{"type":"LineString","arcs":[835]},{"type":"LineString","arcs":[836]},{"type":"LineString","arcs":[837]},{"type":"LineString","arcs":[838]},{"type":"LineString","arcs":[839]},{"type":"LineString","arcs":[840]},{"type":"LineString","arcs":[841]},{"type":"LineString","arcs":[842]},{"type":"LineString","arcs":[843]},{"type":"MultiLineString","arcs":[[844],[845]]},{"type":"LineString","arcs":[846]},{"type":"LineString","arcs":[847]},{"type":"LineString","arcs":[848]},{"type":"LineString","arcs":[849]},{"type":"LineString","arcs":[850]},{"type":"LineString","arcs":[851]},{"type":"LineString","arcs":[852]},{"type":"LineString","arcs":[853]},{"type":"LineString","arcs":[854]},{"type":"MultiLineString","arcs":[[855],[856],[857]]},{"type":"MultiLineString","arcs":[[858],[859]]},{"type":"LineString","arcs":[860]},{"type":"LineString","arcs":[861]},{"type":"LineString","arcs":[862]},{"type":"LineString","arcs":[863]},{"type":"LineString","arcs":[864]},{"type":"LineString","arcs":[865]},{"type":"LineString","arcs":[866]},{"type":"LineString","arcs":[867]},{"type":"LineString","arcs":[868]},{"type":"LineString","arcs":[869]},{"type":"LineString","arcs":[870]},{"type":"LineString","arcs":[871]},{"type":"LineString","arcs":[872]},{"type":"LineString","arcs":[873]},{"type":"LineString","arcs":[874]},{"type":null},{"type":"LineString","arcs":[875]},{"type":"LineString","arcs":[876]},{"type":"LineString","arcs":[877]},{"type":"LineString","arcs":[878]},{"type":"LineString","arcs":[879]},{"type":"LineString","arcs":[880]},{"type":"LineString","arcs":[881]},{"type":"LineString","arcs":[882]},{"type":"LineString","arcs":[883]},{"type":"LineString","arcs":[884]},{"type":"LineString","arcs":[885]},{"type":"LineString","arcs":[886]},{"type":"LineString","arcs":[887]},{"type":"LineString","arcs":[888]},{"type":"LineString","arcs":[889]},{"type":"LineString","arcs":[890]},{"type":"LineString","arcs":[891]},{"type":"LineString","arcs":[892]},{"type":"LineString","arcs":[893]},{"type":"LineString","arcs":[894]},{"type":"LineString","arcs":[895]},{"type":"LineString","arcs":[896]},{"type":"MultiLineString","arcs":[[897],[898]]},{"type":"LineString","arcs":[899]},{"type":"LineString","arcs":[900]},{"type":"LineString","arcs":[901]},{"type":"LineString","arcs":[902]},{"type":"LineString","arcs":[903]},{"type":"LineString","arcs":[904]},{"type":"LineString","arcs":[905]},{"type":"LineString","arcs":[906]},{"type":"LineString","arcs":[907]},{"type":"LineString","arcs":[908]},{"type":"LineString","arcs":[909]},{"type":"LineString","arcs":[910]},{"type":"LineString","arcs":[911]},{"type":"LineString","arcs":[912]},{"type":"LineString","arcs":[913]},{"type":"LineString","arcs":[914]},{"type":"LineString","arcs":[915]},{"type":"LineString","arcs":[916]},{"type":"LineString","arcs":[917]},{"type":"LineString","arcs":[918]},{"type":"LineString","arcs":[919]},{"type":"LineString","arcs":[920]},{"type":"LineString","arcs":[921]},{"type":"LineString","arcs":[922]},{"type":"LineString","arcs":[923]},{"type":"LineString","arcs":[924]},{"type":"LineString","arcs":[925]},{"type":"LineString","arcs":[926]},{"type":"LineString","arcs":[927]},{"type":"LineString","arcs":[928]},{"type":"LineString","arcs":[929]},{"type":"LineString","arcs":[930]},{"type":"LineString","arcs":[931]},{"type":"LineString","arcs":[932]},{"type":"LineString","arcs":[933]},{"type":"LineString","arcs":[934]},{"type":"MultiLineString","arcs":[[935],[936]]},{"type":"LineString","arcs":[937]},{"type":"LineString","arcs":[938]},{"type":"LineString","arcs":[939]},{"type":"LineString","arcs":[940]},{"type":"LineString","arcs":[941]},{"type":"LineString","arcs":[942]},{"type":"LineString","arcs":[943]},{"type":"LineString","arcs":[944]},{"type":"LineString","arcs":[945]},{"type":"LineString","arcs":[946]},{"type":"LineString","arcs":[947]},{"type":"LineString","arcs":[948]},{"type":"LineString","arcs":[949]},{"type":"LineString","arcs":[950]},{"type":"LineString","arcs":[951]},{"type":"LineString","arcs":[952]},{"type":"LineString","arcs":[953]},{"type":"LineString","arcs":[954]},{"type":"LineString","arcs":[955]},{"type":"LineString","arcs":[956]},{"type":"LineString","arcs":[957]},{"type":"LineString","arcs":[958]},{"type":"LineString","arcs":[959]},{"type":"LineString","arcs":[960]},{"type":"LineString","arcs":[961]},{"type":"LineString","arcs":[962]},{"type":"LineString","arcs":[963]},{"type":"LineString","arcs":[964]},{"type":"LineString","arcs":[965]},{"type":"LineString","arcs":[966]},{"type":"LineString","arcs":[967]},{"type":"LineString","arcs":[968]},{"type":"LineString","arcs":[969]},{"type":"LineString","arcs":[970]},{"type":"LineString","arcs":[971]},{"type":"LineString","arcs":[972]},{"type":"LineString","arcs":[973]},{"type":"LineString","arcs":[974]},{"type":"LineString","arcs":[975]},{"type":"LineString","arcs":[976]},{"type":"LineString","arcs":[977]},{"type":"LineString","arcs":[978]},{"type":"LineString","arcs":[979]},{"type":"LineString","arcs":[980]},{"type":"LineString","arcs":[981]},{"type":"LineString","arcs":[982]},{"type":"LineString","arcs":[983]},{"type":"LineString","arcs":[984]},{"type":"LineString","arcs":[985]},{"type":"LineString","arcs":[986]},{"type":"LineString","arcs":[987]},{"type":"LineString","arcs":[988]},{"type":"LineString","arcs":[989]},{"type":"LineString","arcs":[990]},{"type":"LineString","arcs":[991]},{"type":"LineString","arcs":[992]},{"type":"LineString","arcs":[993]},{"type":"LineString","arcs":[994]},{"type":"LineString","arcs":[995]},{"type":"LineString","arcs":[996]},{"type":"LineString","arcs":[997]},{"type":"LineString","arcs":[998]},{"type":"LineString","arcs":[999]},{"type":"LineString","arcs":[1000]},{"type":"LineString","arcs":[1001]},{"type":"LineString","arcs":[1002]},{"type":"LineString","arcs":[1003]},{"type":"LineString","arcs":[1004]},{"type":"LineString","arcs":[1005]},{"type":"LineString","arcs":[1006]},{"type":"LineString","arcs":[1007]},{"type":"LineString","arcs":[1008]},{"type":"LineString","arcs":[1009]},{"type":"LineString","arcs":[1010]},{"type":"LineString","arcs":[1011]},{"type":"LineString","arcs":[1012]},{"type":"LineString","arcs":[1013]},{"type":"LineString","arcs":[1014]},{"type":"LineString","arcs":[1015]},{"type":"LineString","arcs":[1016]},{"type":"LineString","arcs":[1017]},{"type":"MultiLineString","arcs":[[1018],[1019]]},{"type":"LineString","arcs":[1020]},{"type":"LineString","arcs":[1021]},{"type":"LineString","arcs":[1022]},{"type":"MultiLineString","arcs":[[1023],[1024]]},{"type":"MultiLineString","arcs":[[1025],[1026]]},{"type":"MultiLineString","arcs":[[1027],[1028]]},{"type":"LineString","arcs":[1029]},{"type":"LineString","arcs":[1030]},{"type":"LineString","arcs":[1031]},{"type":"LineString","arcs":[1032]},{"type":"LineString","arcs":[1033]},{"type":"LineString","arcs":[1034]},{"type":"LineString","arcs":[1035]},{"type":"LineString","arcs":[1036]},{"type":"LineString","arcs":[1037]},{"type":"MultiLineString","arcs":[[1038],[1039],[1040],[1041]]},{"type":"LineString","arcs":[1042]},{"type":"LineString","arcs":[1043]},{"type":"LineString","arcs":[1044]},{"type":"LineString","arcs":[1045]},{"type":"LineString","arcs":[1046]},{"type":"LineString","arcs":[1047]},{"type":"LineString","arcs":[1048]},{"type":"LineString","arcs":[1049]},{"type":"LineString","arcs":[1050]},{"type":"LineString","arcs":[1051]},{"type":"LineString","arcs":[1052]},{"type":"LineString","arcs":[1053]},{"type":"LineString","arcs":[1054]},{"type":"LineString","arcs":[1055]},{"type":"LineString","arcs":[1056]},{"type":"LineString","arcs":[1057]},{"type":"LineString","arcs":[1058]},{"type":"LineString","arcs":[1059]},{"type":"LineString","arcs":[1060]},{"type":"LineString","arcs":[1061]},{"type":"LineString","arcs":[1062]},{"type":"LineString","arcs":[1063]},{"type":"LineString","arcs":[1064]},{"type":"LineString","arcs":[1065]},{"type":"LineString","arcs":[1066]},{"type":"LineString","arcs":[1067]},{"type":"MultiLineString","arcs":[[1068],[1069]]},{"type":"MultiLineString","arcs":[[1070],[1071],[1072]]},{"type":"LineString","arcs":[1073]},{"type":"LineString","arcs":[1074]},{"type":"LineString","arcs":[1075]},{"type":"LineString","arcs":[1076]},{"type":"LineString","arcs":[1077]},{"type":"LineString","arcs":[1078]},{"type":"LineString","arcs":[1079]},{"type":"MultiLineString","arcs":[[1080],[1081],[1082]]},{"type":"LineString","arcs":[1083]},{"type":"LineString","arcs":[1084]},{"type":"LineString","arcs":[1085]},{"type":"LineString","arcs":[1086]},{"type":"LineString","arcs":[1087]},{"type":"LineString","arcs":[1088]},{"type":"LineString","arcs":[1089]},{"type":"LineString","arcs":[1090]},{"type":"LineString","arcs":[1091]},{"type":"LineString","arcs":[1092]},{"type":"LineString","arcs":[1093]},{"type":"LineString","arcs":[1094]},{"type":"LineString","arcs":[1095]},{"type":"LineString","arcs":[1096]},{"type":"LineString","arcs":[1097]},{"type":"LineString","arcs":[1098]},{"type":"LineString","arcs":[1099]},{"type":"LineString","arcs":[1100]},{"type":"MultiLineString","arcs":[[1101],[1102],[1103],[1104],[1105]]},{"type":"LineString","arcs":[1106]},{"type":"LineString","arcs":[1107]},{"type":"LineString","arcs":[1108]},{"type":"LineString","arcs":[1109]},{"type":"LineString","arcs":[1110]},{"type":"LineString","arcs":[1111]},{"type":"LineString","arcs":[1112]},{"type":"LineString","arcs":[1113]},{"type":"LineString","arcs":[1114]},{"type":"LineString","arcs":[1115]},{"type":"LineString","arcs":[1116]},{"type":"LineString","arcs":[1117]},{"type":"LineString","arcs":[1118]},{"type":"LineString","arcs":[1119]},{"type":"LineString","arcs":[1120]},{"type":"LineString","arcs":[1121]},{"type":"MultiLineString","arcs":[[1122],[1123]]},{"type":"LineString","arcs":[1124]},{"type":"LineString","arcs":[1125]},{"type":"LineString","arcs":[1126]},{"type":"LineString","arcs":[1127]},{"type":"LineString","arcs":[1128]},{"type":"LineString","arcs":[1129]},{"type":"LineString","arcs":[1130]},{"type":"MultiLineString","arcs":[[1131],[1132],[1133]]},{"type":"LineString","arcs":[1134]},{"type":"LineString","arcs":[1135]},{"type":"LineString","arcs":[1136]},{"type":"LineString","arcs":[1137]},{"type":"LineString","arcs":[1138]},{"type":"LineString","arcs":[1139]},{"type":"LineString","arcs":[1140]},{"type":"LineString","arcs":[1141]},{"type":"LineString","arcs":[1142]},{"type":"LineString","arcs":[1143]},{"type":"LineString","arcs":[1144]},{"type":"LineString","arcs":[1145]},{"type":"LineString","arcs":[1146]},{"type":"LineString","arcs":[1147]},{"type":"LineString","arcs":[1148]},{"type":"LineString","arcs":[1149]},{"type":"LineString","arcs":[1150]},{"type":"LineString","arcs":[1151]},{"type":"LineString","arcs":[1152]},{"type":"MultiLineString","arcs":[[1153],[1154]]},{"type":"LineString","arcs":[1155]},{"type":"MultiLineString","arcs":[[1156],[1157],[1158]]},{"type":"LineString","arcs":[1159]},{"type":"LineString","arcs":[1160]},{"type":"LineString","arcs":[1161]},{"type":"LineString","arcs":[1162]},{"type":"LineString","arcs":[1163]},{"type":"LineString","arcs":[1164]},{"type":"LineString","arcs":[1165]},{"type":"LineString","arcs":[1166]},{"type":"LineString","arcs":[1167]},{"type":"LineString","arcs":[1168]},{"type":"MultiLineString","arcs":[[1169],[1170]]},{"type":"LineString","arcs":[1171]},{"type":"LineString","arcs":[1172]},{"type":"LineString","arcs":[1173]},{"type":"LineString","arcs":[67]},{"type":"LineString","arcs":[1174]},{"type":"MultiLineString","arcs":[[1175],[1176]]},{"type":"LineString","arcs":[1177]},{"type":"LineString","arcs":[1178]},{"type":"LineString","arcs":[1179]},{"type":"LineString","arcs":[1180]},{"type":"LineString","arcs":[1181]},{"type":"LineString","arcs":[1182]},{"type":"LineString","arcs":[1183]},{"type":"LineString","arcs":[1184]},{"type":"LineString","arcs":[1185]},{"type":"LineString","arcs":[1186,1187]},{"type":"LineString","arcs":[1188]},{"type":"LineString","arcs":[1189]},{"type":"LineString","arcs":[1190]},{"type":"LineString","arcs":[1191]},{"type":"LineString","arcs":[1192]},{"type":"LineString","arcs":[1193,1194]},{"type":"LineString","arcs":[1195]},{"type":"LineString","arcs":[1196]},{"type":"LineString","arcs":[1197]},{"type":"LineString","arcs":[1198]},{"type":"LineString","arcs":[1199]},{"type":"LineString","arcs":[1200]},{"type":"LineString","arcs":[1201]},{"type":"LineString","arcs":[1202]},{"type":"LineString","arcs":[1203]},{"type":"LineString","arcs":[1204]},{"type":"LineString","arcs":[1205]},{"type":"LineString","arcs":[1206]},{"type":"LineString","arcs":[1207]},{"type":"LineString","arcs":[1208]},{"type":"LineString","arcs":[1209]},{"type":"LineString","arcs":[1210]},{"type":null},{"type":"LineString","arcs":[1211]},{"type":"LineString","arcs":[1212]},{"type":"LineString","arcs":[1213]},{"type":"LineString","arcs":[1214]},{"type":"MultiLineString","arcs":[[1215,1216],[1217]]},{"type":"MultiLineString","arcs":[[1218],[1219]]},{"type":"LineString","arcs":[1220]},{"type":"LineString","arcs":[1221]},{"type":"LineString","arcs":[1222]},{"type":"LineString","arcs":[1223]},{"type":"LineString","arcs":[1224]},{"type":"LineString","arcs":[1225]},{"type":"LineString","arcs":[1226,1227,1228]},{"type":"LineString","arcs":[1229]},{"type":"LineString","arcs":[1230]},{"type":"LineString","arcs":[1231]},{"type":"LineString","arcs":[1232,1227,1233]},{"type":"LineString","arcs":[1234]},{"type":"LineString","arcs":[1235]},{"type":"LineString","arcs":[1236]},{"type":"LineString","arcs":[1237]},{"type":"LineString","arcs":[1238]},{"type":"LineString","arcs":[1239]},{"type":"LineString","arcs":[1240]},{"type":"LineString","arcs":[1241]},{"type":"LineString","arcs":[1242]},{"type":"LineString","arcs":[1243]},{"type":"MultiLineString","arcs":[[1244],[1245],[1246],[1247],[1248]]},{"type":"LineString","arcs":[1249,1250,1251]},{"type":"LineString","arcs":[1252]},{"type":"LineString","arcs":[1253]},{"type":"LineString","arcs":[1254]},{"type":"LineString","arcs":[1255]},{"type":"LineString","arcs":[1256]},{"type":"LineString","arcs":[1257]},{"type":"LineString","arcs":[1258]},{"type":"LineString","arcs":[1259]},{"type":"LineString","arcs":[1260]},{"type":"LineString","arcs":[1261]},{"type":"LineString","arcs":[1262]},{"type":"LineString","arcs":[1263]},{"type":"LineString","arcs":[1264]},{"type":"LineString","arcs":[1265]},{"type":"LineString","arcs":[1266]},{"type":"LineString","arcs":[1267]},{"type":"LineString","arcs":[1268]},{"type":"LineString","arcs":[1269]},{"type":"LineString","arcs":[1270]},{"type":"LineString","arcs":[1271]},{"type":"LineString","arcs":[1272]},{"type":"MultiLineString","arcs":[[1273,1274],[1275,1276]]},{"type":"LineString","arcs":[1277]},{"type":"LineString","arcs":[1278]},{"type":"MultiLineString","arcs":[[1279],[1280]]},{"type":"LineString","arcs":[1281]},{"type":"LineString","arcs":[1282]},{"type":"LineString","arcs":[1283]},{"type":"LineString","arcs":[1284]},{"type":"LineString","arcs":[1285]},{"type":"LineString","arcs":[1286]},{"type":"LineString","arcs":[1287]},{"type":"LineString","arcs":[1288]},{"type":"LineString","arcs":[1289]},{"type":"LineString","arcs":[1290]},{"type":"LineString","arcs":[1291]},{"type":"LineString","arcs":[1292]},{"type":"LineString","arcs":[1293]},{"type":"LineString","arcs":[1294]},{"type":"LineString","arcs":[1295]},{"type":"LineString","arcs":[1296]},{"type":"LineString","arcs":[1297]},{"type":"LineString","arcs":[1298]},{"type":"LineString","arcs":[1299]},{"type":"LineString","arcs":[1300]},{"type":"LineString","arcs":[1301]},{"type":"LineString","arcs":[1302,1303]},{"type":"LineString","arcs":[1304]},{"type":"LineString","arcs":[1305]},{"type":"LineString","arcs":[1306,1307,1308]},{"type":"LineString","arcs":[1309]},{"type":"LineString","arcs":[1310,1311,1312]},{"type":"LineString","arcs":[1313]},{"type":"LineString","arcs":[1314]},{"type":"LineString","arcs":[1315]},{"type":"LineString","arcs":[1316]},{"type":"LineString","arcs":[1317,1318,1319]},{"type":"LineString","arcs":[1320]},{"type":"LineString","arcs":[1321]},{"type":"LineString","arcs":[1322]},{"type":"LineString","arcs":[1323]},{"type":"MultiLineString","arcs":[[1324],[1325]]},{"type":"LineString","arcs":[1326,1327]},{"type":"LineString","arcs":[1328]},{"type":"LineString","arcs":[1329]},{"type":"LineString","arcs":[1330]},{"type":"LineString","arcs":[1331]},{"type":"LineString","arcs":[1332]},{"type":"LineString","arcs":[1333]},{"type":"LineString","arcs":[1334]},{"type":"LineString","arcs":[1335]},{"type":"LineString","arcs":[1336]},{"type":"MultiLineString","arcs":[[1337],[1338],[1339],[1340],[1341]]},{"type":"MultiLineString","arcs":[[1342],[1343]]},{"type":"MultiLineString","arcs":[[1344],[1345],[1346]]},{"type":"MultiLineString","arcs":[[1347],[1348]]},{"type":"LineString","arcs":[1349]},{"type":"LineString","arcs":[1350]},{"type":"LineString","arcs":[1351]},{"type":"LineString","arcs":[1352]},{"type":"LineString","arcs":[1353]},{"type":"MultiLineString","arcs":[[1354],[1355]]},{"type":"LineString","arcs":[1356]},{"type":"LineString","arcs":[1357]},{"type":"MultiLineString","arcs":[[1358],[1359]]},{"type":"LineString","arcs":[1360]},{"type":"LineString","arcs":[1361]},{"type":"LineString","arcs":[1362,1363,1364]},{"type":"LineString","arcs":[1365]},{"type":"LineString","arcs":[1366]},{"type":"LineString","arcs":[1367]},{"type":"LineString","arcs":[1368]},{"type":"LineString","arcs":[1369,1370,1371]},{"type":"LineString","arcs":[1372]},{"type":"LineString","arcs":[1373]},{"type":"MultiLineString","arcs":[[1374,1375],[1376]]},{"type":"LineString","arcs":[1377]},{"type":"LineString","arcs":[1378]},{"type":"LineString","arcs":[1379]},{"type":"LineString","arcs":[1380]},{"type":"LineString","arcs":[1381]},{"type":"LineString","arcs":[1382]},{"type":"LineString","arcs":[1383,1384]},{"type":"LineString","arcs":[1385]},{"type":"LineString","arcs":[1386]},{"type":"LineString","arcs":[1387]},{"type":"LineString","arcs":[1388]},{"type":"LineString","arcs":[1389]},{"type":"LineString","arcs":[1390]},{"type":"LineString","arcs":[1391]},{"type":"LineString","arcs":[1392]},{"type":"LineString","arcs":[1393]},{"type":"LineString","arcs":[1394,1395,1396]},{"type":"LineString","arcs":[1397,1398,1399]},{"type":"LineString","arcs":[1400]},{"type":"LineString","arcs":[1401]},{"type":"LineString","arcs":[1402]},{"type":"LineString","arcs":[1403]},{"type":"LineString","arcs":[1404]},{"type":"LineString","arcs":[1405]},{"type":"LineString","arcs":[1406]},{"type":"LineString","arcs":[1407]},{"type":"LineString","arcs":[1408]},{"type":"LineString","arcs":[1409]},{"type":"LineString","arcs":[1410]},{"type":"LineString","arcs":[1411]},{"type":"LineString","arcs":[1412]},{"type":"LineString","arcs":[1413]},{"type":"LineString","arcs":[1414]},{"type":"LineString","arcs":[1415,1187,1416,1274,1275,1417,1363,1418]},{"type":"LineString","arcs":[1419]},{"type":"LineString","arcs":[1420]},{"type":"LineString","arcs":[1421]},{"type":"LineString","arcs":[1422]},{"type":"LineString","arcs":[1423]},{"type":"LineString","arcs":[1424]},{"type":"LineString","arcs":[1425]},{"type":"LineString","arcs":[1426]},{"type":"LineString","arcs":[1427]},{"type":"LineString","arcs":[1428,1429]},{"type":"LineString","arcs":[1430]},{"type":"LineString","arcs":[1431]},{"type":"LineString","arcs":[1432]},{"type":"LineString","arcs":[1433]},{"type":"LineString","arcs":[1434]},{"type":"LineString","arcs":[1435,1436]},{"type":"LineString","arcs":[1437]},{"type":"LineString","arcs":[1438,1439,1440]},{"type":"LineString","arcs":[1441]},{"type":"LineString","arcs":[1442]},{"type":"LineString","arcs":[1443]},{"type":"LineString","arcs":[1444]},{"type":"LineString","arcs":[1445]},{"type":"LineString","arcs":[1446]},{"type":"LineString","arcs":[1447]},{"type":"LineString","arcs":[1448]},{"type":"LineString","arcs":[1449]},{"type":"LineString","arcs":[1450]},{"type":"LineString","arcs":[1451]},{"type":"LineString","arcs":[1452,1453,1454,1250]},{"type":"LineString","arcs":[1455,-1453]},{"type":"LineString","arcs":[1456]},{"type":"LineString","arcs":[1457]},{"type":"LineString","arcs":[1458]},{"type":"LineString","arcs":[1459]},{"type":"LineString","arcs":[1460]},{"type":"LineString","arcs":[1461]},{"type":"MultiLineString","arcs":[[1462],[1463]]},{"type":"LineString","arcs":[1464]},{"type":"LineString","arcs":[1465]},{"type":"LineString","arcs":[1466]},{"type":"LineString","arcs":[1467,1468]},{"type":"LineString","arcs":[1469]},{"type":"LineString","arcs":[1470,1471,1472]},{"type":"MultiLineString","arcs":[[1473,1471,1474,1475,1035,1476],[1477],[1478],[1479,1213]]},{"type":"LineString","arcs":[1480]},{"type":"MultiLineString","arcs":[[1481],[1482,1483,1484],[1485],[1486,1214]]},{"type":"LineString","arcs":[1487]},{"type":"LineString","arcs":[1488]},{"type":"LineString","arcs":[1489]},{"type":"LineString","arcs":[1490]},{"type":"LineString","arcs":[1491,1492]},{"type":"LineString","arcs":[1493]},{"type":"LineString","arcs":[1494]},{"type":"LineString","arcs":[1495]},{"type":"LineString","arcs":[1496]},{"type":"LineString","arcs":[1497]},{"type":"LineString","arcs":[1498]},{"type":"LineString","arcs":[1499]},{"type":"LineString","arcs":[1500]},{"type":"LineString","arcs":[1501,1502]},{"type":"LineString","arcs":[1503]},{"type":"LineString","arcs":[1504]},{"type":"LineString","arcs":[1505]},{"type":"LineString","arcs":[1506]},{"type":"LineString","arcs":[1507]},{"type":"LineString","arcs":[1508]},{"type":"LineString","arcs":[1509]},{"type":"LineString","arcs":[1510]},{"type":"MultiLineString","arcs":[[1511],[1512]]},{"type":"LineString","arcs":[1513]},{"type":"MultiLineString","arcs":[[1514,1515],[1516]]},{"type":"LineString","arcs":[1517]},{"type":"LineString","arcs":[1518,1519,1520]},{"type":"LineString","arcs":[1521]},{"type":"LineString","arcs":[1522]},{"type":"LineString","arcs":[1523]},{"type":"LineString","arcs":[1524]},{"type":"LineString","arcs":[1525]},{"type":"LineString","arcs":[1526]},{"type":"LineString","arcs":[1527]},{"type":"LineString","arcs":[1528]},{"type":"LineString","arcs":[1529]},{"type":"LineString","arcs":[1530]},{"type":"LineString","arcs":[1531]},{"type":"LineString","arcs":[1532]},{"type":"LineString","arcs":[1533]},{"type":"LineString","arcs":[1534]},{"type":"LineString","arcs":[1535]},{"type":"LineString","arcs":[1536]},{"type":"LineString","arcs":[1537]},{"type":"LineString","arcs":[1538]},{"type":"LineString","arcs":[1539]},{"type":"LineString","arcs":[1540]},{"type":"LineString","arcs":[1541]},{"type":"LineString","arcs":[1542]},{"type":"LineString","arcs":[1543]},{"type":"LineString","arcs":[1544]},{"type":"LineString","arcs":[1545]},{"type":"LineString","arcs":[1546]},{"type":"LineString","arcs":[1547]},{"type":"LineString","arcs":[1548]},{"type":"LineString","arcs":[1549]},{"type":"LineString","arcs":[1550]},{"type":"LineString","arcs":[1551]},{"type":"LineString","arcs":[1552]},{"type":"LineString","arcs":[1553]},{"type":"LineString","arcs":[1554]},{"type":"LineString","arcs":[1555]},{"type":"LineString","arcs":[1556]},{"type":"MultiLineString","arcs":[[1557,1558,1559,1560,1561],[1562,1563,1564]]},{"type":"MultiLineString","arcs":[[1565,1566,1567,1568],[1569,1570]]},{"type":"LineString","arcs":[1571,1572,1573,1574]},{"type":"LineString","arcs":[1575,1576,1577,1578]},{"type":"LineString","arcs":[1579,1580,1581,1582]},{"type":"MultiLineString","arcs":[[1583,1584,1585,1586],[1587,1588,1589,1590,1591],[1592,1593]]},{"type":"LineString","arcs":[1574]},{"type":"LineString","arcs":[1573]},{"type":"LineString","arcs":[1594]},{"type":"LineString","arcs":[1595]},{"type":"LineString","arcs":[1596]},{"type":"LineString","arcs":[1597]},{"type":"LineString","arcs":[1598,1599,1600]},{"type":"LineString","arcs":[1601]},{"type":"LineString","arcs":[1602]},{"type":"LineString","arcs":[1603]},{"type":"LineString","arcs":[1604,1605,1606,1607,1608,1609,1610,1611,1612,1613]},{"type":"MultiLineString","arcs":[[1614,1615,1616,1617,1618,1619],[1620,1621,1622]]},{"type":"MultiLineString","arcs":[[1623],[1624]]},{"type":"LineString","arcs":[1625]},{"type":"LineString","arcs":[1626]},{"type":"LineString","arcs":[1627,1628,1629,1630,1631,1632,1633,584,1634]},{"type":"LineString","arcs":[1635,1303,1636,1637,1638]},{"type":"LineString","arcs":[1639,1640,1641,1642,1643,1644,1645]},{"type":"LineString","arcs":[1646,1647,1648,1649]},{"type":"MultiLineString","arcs":[[1650,1651,1652],[1653,1654,1655,1656]]},{"type":"LineString","arcs":[1657,1658]},{"type":"LineString","arcs":[1659,1660,1661]},{"type":"LineString","arcs":[1662]},{"type":"LineString","arcs":[1663]},{"type":"LineString","arcs":[1664]},{"type":"LineString","arcs":[1665]},{"type":"LineString","arcs":[1666]},{"type":"LineString","arcs":[1667]},{"type":"LineString","arcs":[1668]},{"type":"LineString","arcs":[1669]},{"type":"LineString","arcs":[1670]},{"type":"LineString","arcs":[1671]},{"type":"LineString","arcs":[1672]},{"type":"LineString","arcs":[1673]},{"type":"LineString","arcs":[1674]},{"type":"LineString","arcs":[1675]},{"type":"LineString","arcs":[1676]},{"type":"LineString","arcs":[1677]},{"type":"LineString","arcs":[1678]},{"type":"LineString","arcs":[1679]},{"type":"LineString","arcs":[1680]},{"type":"LineString","arcs":[1681]},{"type":"LineString","arcs":[1682]},{"type":"LineString","arcs":[1683]},{"type":"MultiLineString","arcs":[[1684,1685],[1686]]},{"type":"LineString","arcs":[1687]},{"type":"LineString","arcs":[1688]},{"type":"LineString","arcs":[1689]},{"type":"LineString","arcs":[1690]},{"type":"LineString","arcs":[1691]},{"type":"LineString","arcs":[1692]},{"type":"LineString","arcs":[1693]},{"type":"LineString","arcs":[1694]},{"type":"LineString","arcs":[1695]},{"type":"LineString","arcs":[1696]},{"type":"LineString","arcs":[1697]},{"type":"LineString","arcs":[1698]},{"type":"LineString","arcs":[1699]},{"type":"LineString","arcs":[1700]},{"type":"LineString","arcs":[1701]},{"type":"LineString","arcs":[1702]},{"type":"LineString","arcs":[1703]},{"type":"LineString","arcs":[1704]},{"type":"LineString","arcs":[1705]},{"type":"LineString","arcs":[1706]},{"type":"LineString","arcs":[1707]},{"type":"LineString","arcs":[1708]},{"type":"LineString","arcs":[1709]},{"type":"LineString","arcs":[1710]},{"type":"LineString","arcs":[1711]},{"type":"LineString","arcs":[1712]},{"type":"LineString","arcs":[1713]},{"type":"LineString","arcs":[1714]},{"type":"LineString","arcs":[1715]},{"type":"LineString","arcs":[1716]},{"type":"LineString","arcs":[1717]},{"type":"LineString","arcs":[1718]},{"type":"LineString","arcs":[1719]},{"type":"LineString","arcs":[1720]},{"type":"MultiLineString","arcs":[[1721],[1722],[1723],[1724],[1725]]},{"type":"LineString","arcs":[1726]},{"type":"LineString","arcs":[1727]},{"type":"LineString","arcs":[1728]},{"type":"LineString","arcs":[1729]},{"type":"LineString","arcs":[1730]},{"type":"LineString","arcs":[1731]},{"type":"LineString","arcs":[1732]},{"type":"LineString","arcs":[1733]}]}}}